pam/__init__.py
pam/api.py
pam/cli.py
pam/interface_task_manager.py
pam/server.py
pam/service.py
pam/sqlite.py
pam/task_manager.py
pam/temp_file_utils.py
pam/tester_task.py
pam/utils.py
pam/models/__init__.py
pam/models/request_command.py
pam/templates/buildcmd/pamb
pam/templates/buildcmd/pamb-base.sh
pam/templates/docker/Dockerfile
pam/templates/init/dockerignore.tmpl
pam/templates/init/gitignore.tmpl
pam/templates/init/main.tmpl
pam/templates/init/pylintrc.tmpl
pam/templates/init/run_unit_test.bat
pam/templates/init/run_unit_test.ps1
pam/templates/init/run_unit_test.sh
pam/templates/service/functions.tmpl
pam/templates/service/service.test.tmpl
pam/templates/service/service.yaml
pam/templates/service/service_class.tmpl
pam_python-0.1.30.dist-info/licenses/LICENSE.txt
pam_python-0.1.30.dist-info/METADATA
pam_python-0.1.30.dist-info/WHEEL
pam_python-0.1.30.dist-info/entry_points.txt
pam_python-0.1.30.dist-info/top_level.txt
pam_python-0.1.30.dist-info/RECORD
