Metadata-Version: 2.4
Name: pam-python
Version: 0.1.30
Summary: Pam Python Library
Home-page: https://github.com/heart/pam-python
Author: Narongrit Kanhanoi
Author-email: narongrit@pams.ai
Classifier: Programming Language :: Python :: 3
Classifier: Programming Language :: Python :: 3.8
Classifier: Programming Language :: Python :: 3.9
Classifier: License :: Other/Proprietary License
Classifier: Operating System :: OS Independent
Classifier: Intended Audience :: Developers
Classifier: Intended Audience :: Customer Service
Classifier: Topic :: Software Development :: Libraries
Requires-Python: >=3.8
License-File: LICENSE.txt
Requires-Dist: setuptools>=70.0.0
Requires-Dist: Flask>=3.0.2
Requires-Dist: aiohttp>=3.11.11
Requires-Dist: pandas>=2.2.3
Requires-Dist: Faker>=33.1.0
Requires-Dist: dask>=2024.12.1
Requires-Dist: dask-expr>=1.1.21
Requires-Dist: requests>=2.32.3
Requires-Dist: gunicorn>=23.0.0
Requires-Dist: pyarrow>=19.0.1
Dynamic: author
Dynamic: author-email
Dynamic: classifier
Dynamic: description
Dynamic: description-content-type
Dynamic: home-page
Dynamic: license-file
Dynamic: requires-dist
Dynamic: requires-python
Dynamic: summary
